{
    "phonebook": [
      {
        "sn_no": 1,
        "name": "John Doe",
        "email": "johndoe@example.com",
        "mobile_number": "+1234567890"
      },
      {
        "sn_no": 2,
        "name": "Jane Smith",
        "email": "janesmith@example.com",
        "mobile_number": "+1234567891"
      },
      {
        "sn_no": 3,
        "name": "Robert Brown",
        "email": "robertbrown@example.com",
        "mobile_number": "+1234567892"
      },
      {
        "sn_no": 4,
        "name": "Emily Davis",
        "email": "emilydavis@example.com",
        "mobile_number": "+1234567893"
      },
      {
        "sn_no": 5,
        "name": "Michael Wilson",
        "email": "michaelwilson@example.com",
        "mobile_number": "+1234567894"
      },
      {
        "sn_no": 6,
        "name": "Sarah Taylor",
        "email": "sarahtaylor@example.com",
        "mobile_number": "+1234567895"
      },
      {
        "sn_no": 7,
        "name": "David Moore",
        "email": "davidmoore@example.com",
        "mobile_number": "+1234567896"
      },
      {
        "sn_no": 8,
        "name": "Linda Anderson",
        "email": "lindaanderson@example.com",
        "mobile_number": "+1234567897"
      },
      {
        "sn_no": 9,
        "name": "James Thomas",
        "email": "jamesthomas@example.com",
        "mobile_number": "+1234567898"
      },
      {
        "sn_no": 10,
        "name": "Barbara Jackson",
        "email": "barbarajackson@example.com",
        "mobile_number": "+1234567899"
      },
      {
        "sn_no": 11,
        "name": "William Harris",
        "email": "williamharris@example.com",
        "mobile_number": "+1234567800"
      },
      {
        "sn_no": 12,
        "name": "Elizabeth Martin",
        "email": "elizabethmartin@example.com",
        "mobile_number": "+1234567801"
      },
      {
        "sn_no": 13,
        "name": "Christopher Thompson",
        "email": "christopherthompson@example.com",
        "mobile_number": "+1234567802"
      },
      {
        "sn_no": 14,
        "name": "Patricia Martinez",
        "email": "patriciamartinez@example.com",
        "mobile_number": "+1234567803"
      },
      {
        "sn_no": 15,
        "name": "Daniel White",
        "email": "danielwhite@example.com",
        "mobile_number": "+1234567804"
      },
      {
        "sn_no": 16,
        "name": "Jennifer Lee",
        "email": "jenniferlee@example.com",
        "mobile_number": "+1234567805"
      },
      {
        "sn_no": 17,
        "name": "Matthew Clark",
        "email": "matthewclark@example.com",
        "mobile_number": "+1234567806"
      },
      {
        "sn_no": 18,
        "name": "Jessica Lewis",
        "email": "jessicalewis@example.com",
        "mobile_number": "+1234567807"
      },
      {
        "sn_no": 19,
        "name": "Joshua Walker",
        "email": "joshuawalker@example.com",
        "mobile_number": "+1234567808"
      },
      {
        "sn_no": 20,
        "name": "Margaret Hall",
        "email": "margarethall@example.com",
        "mobile_number": "+1234567809"
      },
      {
        "sn_no": 21,
        "name": "Andrew Allen",
        "email": "andrewallen@example.com",
        "mobile_number": "+1234567810"
      },
      {
        "sn_no": 22,
        "name": "Rebecca Young",
        "email": "rebeccayoung@example.com",
        "mobile_number": "+1234567811"
      },
      {
        "sn_no": 23,
        "name": "Joshua Hernandez",
        "email": "joshuahernandez@example.com",
        "mobile_number": "+1234567812"
      },
      {
        "sn_no": 24,
        "name": "Linda King",
        "email": "lindaking@example.com",
        "mobile_number": "+1234567813"
      },
      {
        "sn_no": 25,
        "name": "Matthew Wright",
        "email": "matthewwright@example.com",
        "mobile_number": "+1234567814"
      },
      {
        "sn_no": 26,
        "name": "Joshua Lopez",
        "email": "joshualopez@example.com",
        "mobile_number": "+1234567815"
      },
      {
        "sn_no": 27,
        "name": "Deborah Hill",
        "email": "deborahhill@example.com",
        "mobile_number": "+1234567816"
      },
      {
        "sn_no": 28,
        "name": "Daniel Scott",
        "email": "danielscott@example.com",
        "mobile_number": "+1234567817"
      },
      {
        "sn_no": 29,
        "name": "Jessica Green",
        "email": "jessicagreen@example.com",
        "mobile_number": "+1234567818"
      },
      {
        "sn_no": 30,
        "name": "Jennifer Adams",
        "email": "jenniferadams@example.com",
        "mobile_number": "+1234567819"
      },
      {
        "sn_no": 31,
        "name": "Mark Baker",
        "email": "markbaker@example.com",
        "mobile_number": "+1234567820"
      },
      {
        "sn_no": 32,
        "name": "Patricia Gonzalez",
        "email": "patriciagonzalez@example.com",
        "mobile_number": "+1234567821"
      },
      {
        "sn_no": 33,
        "name": "Charles Nelson",
        "email": "charlesnelson@example.com",
        "mobile_number": "+1234567822"
      },
      {
        "sn_no": 34,
        "name": "Jessica Carter",
        "email": "jessicacarter@example.com",
        "mobile_number": "+1234567823"
      },
      {
        "sn_no": 35,
        "name": "Michael Mitchell",
        "email": "michaelmitchell@example.com",
        "mobile_number": "+1234567824"
      },
      {
        "sn_no": 36,
        "name": "Patricia Perez",
        "email": "patriciaperez@example.com",
        "mobile_number": "+1234567825"
      },
      {
        "sn_no": 37,
        "name": "Linda Roberts",
        "email": "lindaroberts@example.com",
        "mobile_number": "+1234567826"
      },
      {
        "sn_no": 38,
        "name": "Robert Turner",
        "email": "robertturner@example.com",
        "mobile_number": "+1234567827"
      },
      {
        "sn_no": 39,
        "name": "Elizabeth Phillips",
        "email": "elizabethphillips@example.com",
        "mobile_number": "+1234567828"
      },
      {
        "sn_no": 40,
        "name": "David Campbell",
        "email": "davidcampbell@example.com",
        "mobile_number": "+1234567829"
      },
      {
        "sn_no": 41,
        "name": "Elizabeth Parker",
        "email": "elizabethparker@example.com",
        "mobile_number": "+1234567830"
      },
      {
        "sn_no": 42,
        "name": "James Evans",
        "email": "jamesevans@example.com",
        "mobile_number": "+1234567831"
      },
      {
        "sn_no": 43,
        "name": "John Edwards",
        "email": "johnedwards@example.com",
        "mobile_number": "+1234567832"
      },
      {
        "sn_no": 44,
        "name": "Daniel Collins",
        "email": "danielcollins@example.com",
        "mobile_number": "+1234567833"
      },
      {
        "sn_no": 45,
        "name": "Michael Stewart",
        "email": "michaelstewart@example.com",
        "mobile_number": "+1234567834"
      },
      {
        "sn_no": 46,
        "name": "Sarah Sanchez",
        "email": "sarahsanchez@example.com",
        "mobile_number": "+1234567835"
      },
      {
        "sn_no": 47,
        "name": "Elizabeth Morris",
        "email": "elizabethmorris@example.com",
        "mobile_number": "+1234567836"
      },
      {
        "sn_no": 48,
        "name": "William Rogers",
        "email": "williamrogers@example.com",
        "mobile_number": "+1234567837"
      },
      {
        "sn_no": 49,
        "name": "Charles Reed",
        "email": "charlesreed@example.com",
        "mobile_number": "+1234567838"
      },
      {
        "sn_no": 50,
        "name": "David Cook",
        "email": "davidcook@example.com",
        "mobile_number": "+1234567839"
      }
    ]
  }
  